Upscalin/__init__.py
Upscalin/__main__.py
Upscalin/Resources/Images/Upscalin.png
Upscalin/Resources/Images/Upscalin.svg
upscalin-0.6.0.dist-info/METADATA
upscalin-0.6.0.dist-info/WHEEL
upscalin-0.6.0.dist-info/entry_points.txt
upscalin-0.6.0.dist-info/RECORD
