Metadata-Version: 2.3
Name: upscalin
Version: 0.6.0
Summary: A Convenience Multi-Upscalers for Video, Images. Batch Processing, Multithreaded.
Project-URL: Changelog, https://brokensrc.dev/news/category/releases
Project-URL: GitHub, https://github.com/BrokenSource/Upscalin
Project-URL: Funding, https://brokensrc.dev/about/sponsors
Project-URL: Contact, https://brokensrc.dev/about/contact
Project-URL: Download, https://brokensrc.dev/get/releases
Project-URL: Docs, https://brokensrc.dev/upscalin
Project-URL: Homepage, https://brokensrc.dev
Author-email: Tremeschin <29046864+Tremeschin@users.noreply.github.com>
License-Expression: AGPL-3.0
Requires-Python: >=3.9
Requires-Dist: broken-source==0.6.0
